marionette/__init__.py
marionette/action.py
marionette/channel.py
marionette/channel_manual.py
marionette/client.py
marionette/conf.py
marionette/driver.py
marionette/dsl.py
marionette/exceptions.py
marionette/executable.py
marionette/format_validator.py
marionette/marionette.conf
marionette/multiplexer.py
marionette/record_layer.py
marionette/server.py
marionette/updater.py
marionette/executables/__init__.py
marionette/executables/pioa.py
marionette/formats/__init__.py
marionette/formats/20150701/__init__.py
marionette/formats/20150701/dns_request.mar
marionette/formats/20150701/dummy.mar
marionette/formats/20150701/ftp_pasv_transfer.mar
marionette/formats/20150701/ftp_simple_blocking.mar
marionette/formats/20150701/http_active_probing.mar
marionette/formats/20150701/http_active_probing2.mar
marionette/formats/20150701/http_probabilistic_blocking.mar
marionette/formats/20150701/http_simple_blocking.mar
marionette/formats/20150701/http_simple_blocking_with_msg_lens.mar
marionette/formats/20150701/http_simple_nonblocking.mar
marionette/formats/20150701/http_squid_blocking.mar
marionette/formats/20150701/http_timings.mar
marionette/formats/20150701/https_simple_blocking.mar
marionette/formats/20150701/smb_simple_nonblocking.mar
marionette/formats/20150701/ssh_simple_nonblocking.mar
marionette/formats/20150701/test_hex_input_strings.mar
marionette/formats/20150701/udp_test_format.mar
marionette/formats/20150701/active_probing/__init__.py
marionette/formats/20150701/active_probing/ftp_pureftpd_10.mar
marionette/formats/20150701/active_probing/http_apache_247.mar
marionette/formats/20150701/active_probing/ssh_openssh_661.mar
marionette/formats/20150701/nmap/__init__.py
marionette/formats/20150701/nmap/kpdyer.com.mar
marionette/formats/20150701/ta/amzn_conn.mar
marionette/formats/20150701/ta/amzn_sess.mar
marionette/formats/20150702/http_simple_blocking.mar
marionette/plugins/__init__.py
marionette/plugins/_channel.py
marionette/plugins/_fte.py
marionette/plugins/_io.py
marionette_tg-0.2.0.dist-info/licenses/LICENSE
marionette_tg-0.2.0.dist-info/METADATA
marionette_tg-0.2.0.dist-info/WHEEL
marionette_tg-0.2.0.dist-info/top_level.txt
marionette_tg-0.2.0.dist-info/RECORD
