Metadata-Version: 2.4
Name: marionette-tg
Version: 0.2.0
Summary: Marionette - The polymorphic, programmable proxy.
Home-page: https://github.com/marionette-tg/marionette
Author: Kevin P. Dyer
Author-email: kpdyer@gmail.com
License: MIT
Classifier: Development Status :: 3 - Alpha
Classifier: Intended Audience :: Developers
Classifier: License :: OSI Approved :: MIT License
Classifier: Operating System :: OS Independent
Classifier: Programming Language :: Python :: 3
Classifier: Programming Language :: Python :: 3.8
Classifier: Programming Language :: Python :: 3.9
Classifier: Programming Language :: Python :: 3.10
Classifier: Programming Language :: Python :: 3.11
Classifier: Programming Language :: Python :: 3.12
Classifier: Topic :: Internet :: Proxy Servers
Classifier: Topic :: Security
Requires-Python: >=3.8
License-File: LICENSE
Requires-Dist: twisted>=25.5.0
Requires-Dist: fte>=0.2.1
Requires-Dist: ply>=3.11
Requires-Dist: requests>=2.28.0
Requires-Dist: PySocks>=1.7.0
Dynamic: author
Dynamic: author-email
Dynamic: classifier
Dynamic: description
Dynamic: description-content-type
Dynamic: home-page
Dynamic: license
Dynamic: license-file
Dynamic: requires-dist
Dynamic: requires-python
Dynamic: summary
